{
    "whitelist_tags": [
        "label",
        "labelShort",
        "pawnLabel",
        "description",
        "reportString",
        "jobString",
        "verb",
        "gerund",
        "helpText",
        "text",
        "title",
        "baseInspectLine",
        "inspectString",
        "explanation",
        "summary",
        "tooltip",
        "letterLabel",
        "letterText",
        "notification"
    ],
    "blacklist_tags": [
        "defName",
        "modContentPack",
        "modMetaData",
        "Abstract",
        "workerClass",
        "driverClass",
        "graphicData",
        "texture",
        "sound",
        "costList",
        "thingClass",
        "statBases",
        "comps",
        "verbs"
    ],
    "blacklist_patterns": [
        "internal_",
        "debug_",
        "tmp_",
        "icon",
        "texture",
        "sprite",
        "gfx",
        "sound_",
        "audio_",
        "shader",
        "mesh",
        "costList"
    ],
    "keyed_as_direct": [],
    "aggressive_fallback": false,
    "min_text_length": 2,
    "priority_suffixes": [
        "label",
        "description",
        "reportString",
        "jobString",
        "title",
        "text",
        "tooltip"
    ]
}